autoscheduler/__init__.py
autoscheduler/_divideResults.py
autoscheduler/_executeCircuitAWS.py
autoscheduler/_executeCircuitIBM.py
autoscheduler/_translator.py
autoscheduler/_version.py
autoscheduler/autoscheduler.py
autoscheduler-1.2.1.dist-info/licenses/LICENSE
autoscheduler-1.2.1.dist-info/METADATA
autoscheduler-1.2.1.dist-info/WHEEL
autoscheduler-1.2.1.dist-info/top_level.txt
autoscheduler-1.2.1.dist-info/RECORD
