Metadata-Version: 2.4
Name: autoscheduler
Version: 1.2.1
Summary: A library for quantum circuit composition
Author-email: Jorge Casco Seco <jorgecs@unex.es>
License-Expression: MIT
Project-URL: Homepage, https://github.com/Qcraft-UEx/QCRAFT-AutoScheduler
Project-URL: Changelog, https://github.com/Qcraft-UEx/QCRAFT-AutoScheduler/blob/main/CHANGELOG.md
Keywords: quantum,quantum computing,quantum circuit optimization,circuit cost reduction,qiskit,braket
Classifier: Development Status :: 4 - Beta
Classifier: Intended Audience :: Developers
Classifier: Intended Audience :: Science/Research
Classifier: Programming Language :: Python :: 3.9
Classifier: Programming Language :: Python :: 3.10
Classifier: Programming Language :: Python :: 3.11
Classifier: Programming Language :: Python :: 3.12
Classifier: Programming Language :: Python :: 3.13
Classifier: Topic :: Scientific/Engineering
Classifier: Topic :: Scientific/Engineering :: Physics
Classifier: Topic :: Software Development :: Libraries :: Python Modules
Requires-Python: >=3.9
License-File: LICENSE
Requires-Dist: requests<3.0.0,>=2.32.0
Requires-Dist: qiskit<3.0.0,>=1.1.0
Requires-Dist: amazon-braket-sdk<2.0.0,>=1.80.0
Requires-Dist: qiskit-ibm-runtime<1.0.0,>=0.23.0
Requires-Dist: qiskit-aer<1.0.0,>=0.14.2
Requires-Dist: antlr4-python3-runtime==4.9.2
Provides-Extra: dev
Requires-Dist: pytest; extra == "dev"
Requires-Dist: sphinx; extra == "dev"
Dynamic: license-file
